cing/__init__.py
kucingganteng-0.1.0.dist-info/METADATA
kucingganteng-0.1.0.dist-info/WHEEL
kucingganteng-0.1.0.dist-info/top_level.txt
kucingganteng-0.1.0.dist-info/RECORD
